{
  "configuracoes": {
    "entradas": {
      "promptParaDeletar": true
    },
    "todos": {
      "promptParaDeletar": true
    }
  },
  "entradas": [
    {
      "id": "7c6822d7-b553-4bdb-85cd-87f3fc4697f3",
      "nome": "teste",
      "quantidade": 131233,
      "pago": false
    }
  ],
  "todos": [
    {
      "id": "519b7d42-ff99-4d0f-ab8d-0d8538a4659c",
      "descricao": "testeeee",
      "concluido": false
    },
    {
      "id": "25421616-0d37-4992-9fc7-7146b6e60d77",
      "descricao": "testeee",
      "concluido": false
    },
    {
      "id": "ba38ef8a-381d-4b7f-a902-6aafb6fd3d26",
      "descricao": "teste",
      "concluido": false
    },
    {
      "id": "4a296a75-64e8-4dce-a3c2-3819b0cf52fc",
      "descricao": "teste",
      "concluido": false
    }
  ]
}